LICENSE.txt
MANIFEST.in
README.md
pyproject.toml
setup.py
src/test_all.py
src/mercury_settrie.egg-info/PKG-INFO
src/mercury_settrie.egg-info/SOURCES.txt
src/mercury_settrie.egg-info/dependency_links.txt
src/mercury_settrie.egg-info/top_level.txt
src/settrie/SetTrie.py
src/settrie/__init__.py
src/settrie/create_tutorials.py
src/settrie/imports.in
src/settrie/main.dox
src/settrie/py_settrie.i
src/settrie/py_settrie_wrap.cpp
src/settrie/settrie.cpp
src/settrie/settrie.h
src/settrie/st_main.cpp
src/settrie/st_main.h
src/settrie/tutorials/settrie_benchmark.ipynb
src/settrie/tutorials/settrie_benchmark_colab.ipynb
src/settrie/tutorials/settrie_data.tar.gz