Metadata-Version: 2.1
Name: mercury-settrie
Version: 1.5.1
Summary: A SetTrie is a container of sets that performs efficient subset and superset queries.
Author-email: Mercury Team <mercury.group@bbva.com>
License:                          Apache License
Keywords: event detection,event prediction,time series
Classifier: Programming Language :: Python :: 3
Classifier: License :: OSI Approved :: Apache Software License
Classifier: Operating System :: OS Independent
Requires-Python: >=3.8
License-File: LICENSE.txt
